ib2parqet/__init__.py
ib2parqet/__main__.py
ib2parqet/_version.py
ib2parqet/ib2parqet.py
ib2parqet-1.0.2.dist-info/LICENSE
ib2parqet-1.0.2.dist-info/METADATA
ib2parqet-1.0.2.dist-info/WHEEL
ib2parqet-1.0.2.dist-info/entry_points.txt
ib2parqet-1.0.2.dist-info/top_level.txt
ib2parqet-1.0.2.dist-info/RECORD
