Metadata-Version: 2.1
Name: ib2parqet
Version: 1.0.2
Summary: converts Interactive Brokers Flex Reports to csv importable by Parqet
Home-page: https://gitlab.com/martizih/ib2parqet.git
Author: Martin Zihlmann
Author-email: martizih@outlook.com
License: MIT
Classifier: Programming Language :: Python :: 3
Classifier: License :: Other/Proprietary License
Classifier: Operating System :: OS Independent
Requires-Python: >=3
License-File: LICENSE
Requires-Dist: xmltodict
Requires-Dist: python-dateutil
